{
    "Version": "2012-10-17",
    "Statement": [
        {
            "Sid": "VisualEditor0",
            "Effect": "Allow",
            "Action": [
                "eks:ListNodegroups",
                "eks:DescribeFargateProfile",
                "eks:ListTagsForResource",
                "eks:ListAddons",
                "eks:UpdateClusterConfig",
                "eks:DescribeAddon",
                "eks:ListFargateProfiles",
                "eks:DescribeNodegroup",
                "eks:DescribeIdentityProviderConfig",
                "eks:ListUpdates",
                "eks:DescribeUpdate",
                "eks:AccessKubernetesApi",
                "eks:DescribeCluster",
                "eks:ListIdentityProviderConfigs"
            ],
            "Resource": "arn:aws:eks:us-east-1:047923129740:cluster/clo835"
        },
        {
            "Sid": "VisualEditor1",
            "Effect": "Allow",
            "Action": [
                "eks:ListClusters",
                "eks:DescribeAddonVersions"
            ],
            "Resource": "*"
        }
    ]
}